sequential/pcupdate/pcupdate.v
`timescale 1ns/1ps

module pcupdate(clk,icode,cnd,valC,valM,valP,pc);
input [3:0] icode;
input cnd;
input clk;
input [63:0] valC;
input [63:0] valM;
input [10:0] valP;
output [10:0] pc;
reg [10:0] pc;
initial begin pc = 0;
end
always@(posedge clk)
begin
	
	if(icode == 1 || icode == 2 || icode == 3 || icode == 4 || icode == 5 || icode == 6 || icode == 10 ||icode == 11)
	     pc = valP;
	else if(icode == 7)
	begin
		if(cnd == 1)
		begin
			pc = valC;
		end
		else
			pc = valP;
	end
	else if(icode == 8)
		pc = valC;
	else if (icode == 9)
		pc = valM;
	$display("update -- icode - %h, cnd - %h, valP - %h, valC - %h,valM - %h ,  pc - %h",icode,cnd,valP,valC,valM,pc);
end
endmodule

sequential/memory/memory.v
`timescale 1ns/1ps

module memory(icode,valA,valE,valP,valM,imem_error,instr_valid,dmem_error,stat,e_com);
input [3:0] icode;
input [63:0] valA;
input [10:0] valP;
input [63:0] valE;
output [63:0] valM;
output dmem_error;
input imem_error;
input instr_valid;
output [1:0] stat;
reg [1:0] stat;
// defining memory block
reg [63:0] mem[0:200];
input e_com;
/*
initial begin
	mem[0] =0;
	mem[1] = 1;
	mem[2] = 10;
	mem[3] = 3;
	mem[4] = 4;
	mem[5] = 5;
	mem[6] =6;
	mem[7] = 7;
end
*/
reg read ;
reg dmem_error;
reg [63:0] valM;
reg write ;
reg [63:0] address;
reg [63:0] data;
/*
mem_read call1(icode,read);
mem_write call2(icode,write);
mem_address call3(icode,valE,valA,address);
mem_data call4(icode,data,valA,valP);
*/
always @(posedge e_com)
begin
	dmem_error = 0;
	// read logic
	read =0;
	if(icode == 11 || icode == 5 || icode== 9)
		read = 1;
	// write logic
	write = 0;
	if (icode == 4 || icode == 8 || icode == 10)
	begin
		write = 1;
	end
	
	// address logic
	address = 0;
	if(icode  == 9 || icode == 11 )
		address = valA;
	else if(icode == 5 || icode == 4 || icode == 10 || icode == 8)
		address = valE;	

	// data logic
	data = 0;
	if(icode == 4 || icode == 10)
	begin
		data = valA;
	end
	else if(icode == 8)
	begin
		data = valP;
	end

	// memory read or write
	if(address>200)
	begin
		dmem_error = 1;
	end
	else if(write === 1)
	begin
		mem[address] = data;	
		$display("write - %d %d %d %d", address,data,valE,valA);
	end
	else if(read === 1)
	begin
		valM = mem[address];
		$display("read -%d %d %d %d" ,valM,address,valE,valA);
	end
	
	// stat code updating
	if(imem_error || dmem_error) stat = 1;
	else if(!instr_valid) stat = 2;
	else if(icode ==0) stat =3;
	else stat = 0;

	if(stat == 0) $display("stat - SAOK , icode - %h\n",icode);
	else if(stat == 1) begin $display("stat - SADR , icode - %h\n",address); $finish; end
	else if(stat == 2) begin $display("stat - SINS , icode - %h\n",icode); $finish; end
	else if(stat == 3) begin $display("stat -SHLT , icode - %h\n",icode); $finish; end
	$display("Memory -- icode - %h, address - %h, data - %h, read - %h , write - %h",icode, address, data, read, write);
end
endmodule

module mem_read(icode,read);
input [3:0] icode;
output read;
reg read;
always @(*)
begin
	read =0;
	if(icode == 11 || icode == 5 || icode== 9)
		read = 1;
end
endmodule

module mem_write(icode,write);
input [3:0] icode;
output write;
reg write;

always@ (*)
begin
	write = 0;
	if (icode == 4 || icode == 8 || icode == 10)
	begin
		write = 1;
	end
end
endmodule


module mem_address(icode,valE,valA,address);
input [3:0] icode;
input [63:0] valE;
input [63:0] valA;
output [63:0] address;

reg [63:0] address;

always@(*)
begin
	address = 0;
	if(icode  == 9 || icode == 11 )
		address = valA;
	else if(icode == 5 || icode == 4 || icode == 10 || icode == 8)
		address = valE;	
end
endmodule

module mem_data(icode,data,valA,valP);
input [3:0] icode;
input [63:0] valA;
input [10:0] valP;
output [63:0] data;

reg [63:0] data;

always @(*)
begin
	data = 0;
	if(icode == 4 || icode == 10)
	begin
		data = valA;
	end
	else if(icode == 8)
	begin
		data = valP;
	end

end
endmodule

sequential/alu/alu.v
`timescale 1ns/1ps

module alu(icode,ifun,valA,valB,valC,valE,cnd,d_com,e_com);
input [63:0] valA;
input [63:0] valB;
input [63:0] valC;
output [63:0] valE;
output cnd;
input [3:0] icode;
input [3:0] ifun;
reg cnd;
reg [63:0] valE;
reg [2:0] cc;
input d_com;
output reg e_com;
initial begin
	cc[0] = 0;
	cc[1] = 0;
	cc[2] = 0;
end
reg [63:0] a;
reg [63:0] b;
reg [2:0] fun;
//aluA call1(icode,valC,valA,a);
//aluB call2(icode,valB,b);
//aluFun call3(icode,ifun,fun);
//cond call4(ifun,cc,cnd);

always @(posedge d_com)
begin
	// aluA logic 
	e_com = 0;
	if(icode == 2 || icode ==6)
		a = valA;
	else if(icode == 3 || icode== 4 || icode == 5) 
		a = valC;
	else if(icode == 8 || icode == 10) 
		a = -1;
	else if(icode == 9 || icode == 11)
		a = 1;

	// aluB logic
	if(icode == 3 || icode == 2) b = 0;
	else if (icode == 4 || icode == 5 || icode ==6 || icode == 8 ||  icode ==10 )
	       b = valB;
       else if(icode ==9||icode==11)
	       b =valA;
       //alu fun logic
	if(icode == 6)
		fun = ifun;
	else if(icode == 2 || icode ==3 || icode ==4 || icode == 5 || icode == 8 || icode == 9|| icode == 10 || icode == 11)
		fun = 0;

	// --- ALU---
	if(icode == 2 || icode == 3 || icode ==4 || icode == 5 || icode == 8 || icode == 9|| icode == 10 || icode == 11)
	begin 
		valE = a+b;
	end
	else if(icode == 6)
	begin
		cc = 0;
		if(fun ==0)
		begin
		valE = a+b;
		//setting the condtion code register cc;
		if(valE == 0)
			cc[0] = 1;
		if (valE[63]==1)
			cc[1] =1;
		if( (valE[63]==1 && a[63]==0 && b[63]==0) || (valE[63]==0 && a[63]==1 && a[63]==1))
			cc[2] =1;
		end
		if(fun ==1)
		begin
		valE = b+(-a);
		//setting the condtion code register cc;
		if(valE == 0)
			cc[0] = 1;
		if (valE[63]==1)
			cc[1] =1;
		if( (valE[63]==0 && a[63]==0 && b[63]==1) || (valE[63]==1 && a[63]==1 && b[63]==0))
			cc[2] =1;
		end
		if(fun ==2)
		begin
		valE = b&a;
		//setting the condtion code register cc;
		if(valE == 0)
			cc[0] = 1;
		end
		if(fun ==3)
		begin
		valE = b^a;
		//setting the condtion code register cc;
		if(valE == 0)
			cc[0] = 1;
		end	
	end
	// alu condition logic	
	if (icode == 7 || icode == 2)
	begin
	cnd = 0;
	if (ifun == 0)
		cnd = 1;
	else if(ifun == 1 && (cc[0] |(cc[1]^cc[2]))==1)
		cnd = 1;
	else if(ifun == 2 &&  (cc[1]^cc[2] == 1))
		cnd = 1;
	else if(ifun == 3 && (cc[0] == 1 ))
		cnd = 1;
	else if(ifun == 4 && (cc[0] == 0))
		cnd = 1;
	else if(ifun == 5 && (cc[0] == 1 || (cc[1]^cc[2] == 0)))
		cnd = 1;
	else if(ifun == 6 && (cc[1]^ cc[2] == 0) && cc[0]==0)
		cnd = 1;
	//$display("execute condition register , icode - %d, over,neg,zero -%b",icode,cc);
	end
	$display("Execute -- icode - %h ,ifun - %h, valA - %d, valB -%d, valC - %d, valE - %d, over,neg,zero - %b", icode,ifun,valA,valB,valC,valE,cc);
	
	e_com = 1;	
end
endmodule
/*
module aluA(icode,valC,valA,a);
input [3:0]  icode;
input [63:0] valC;
input [63:0] valA;
output [63:0] a;
reg [63:0] a;

always@(*)
begin
	if(icode == 2 || icode ==6)
		a = valA;
	else if(icode == 3 || icode== 4 || icode == 5) 
		a = valC;
	else if(icode == 8 || icode == 10) 
		a = -1;
	else if(icode == 9 || icode == 11)
		a = 1;
end
endmodule

module aluB(icode,valB,b);
input [3:0] icode;
input [63:0] valB;
output [63:0] b;
reg [63:0] b;

always @ (*)
begin
	if(icode == 3 || icode == 2) b = 0;
	else if (icode == 4 || icode == 5 || icode ==6 || icode == 8 || icode == 9 || icode ==10 ||icode==11)
	       b = valB;	
end

endmodule

module aluFun(icode,ifun,fun);
input [3:0] icode;
input [3:0] ifun;
output [2:0] fun;
reg [2:0] fun;

always @(*)
begin
	if(icode == 6)
		fun = ifun;
	else if(icode == 2 || icode ==3 || icode ==4 || icode == 5 || icode == 8 || icode == 9|| icode == 10 || icode == 11)
		fun = 0;
end
endmodule

module cond(ifun,cc,cnd);
input [3:0] ifun;
input [2:0] cc;
output cnd;
reg cnd;

always@(*)
begin
	cnd = 0;
	if(ifun == 1 && (cc[0] == 1 || (cc[1]==1 && cc[2] == 0)))
		cnd = 1;

	else if(ifun == 2 &&  (cc[1]==1 && cc[2] == 0))
		cnd = 1;
	else if(ifun == 3 && (cc[0] == 1 ))
		cnd = 1;
	else if(ifun == 4 && (cc[0] == 0))
		cnd = 1;
	else if(ifun == 5 && (cc[0] == 1 ||(cc[1] == 0 && cc[2] == 0)))
		cnd = 1;
	else if(ifun == 6 && (cc[1] == 0 && cc[2] == 0))
		cnd = 1;
end
endmodule*/

sequential/decode_writeback/decode.v
`timescale 1ns/1ps

module decode(clk,icode,rA,rB,valA,valB,valE,valM,cnd,d_com,f_com);
input clk;
input [3:0] icode;
input [3:0] rA;
input [3:0] rB;
output [63:0] valA;
output [63:0] valB;
//input [3:0] dstE;
//input [3:0] dstM;
input [63:0] valE;
input [63:0] valM;
output reg complete;
input cnd;
input f_com;
output reg d_com;
reg [63:0] r1Val, r2Val,r0Val;
// reg file defining 
reg signed [63:0] reg_file [0:15];

initial begin
	reg_file[0] = 0;
	reg_file[1] = 0;
	reg_file[2] = 0;
	reg_file[3] = 0;
	reg_file[4] = 128;
	reg_file[5] = 0;
	reg_file[6] = 0;
	reg_file[7] = 0;
	reg_file[8] = 0;
	reg_file[9] = 0;
	reg_file[10] =00;
	reg_file[11] = 0;
	reg_file[12] = 0;
	reg_file[13] = 0;
	reg_file[14] = 0;
	reg_file[15] =0;
end

reg [63:0] valA;
reg [63:0] valB;
reg [3:0] dstE;
reg [3:0] dstM;
// ------ Decode stage  ------  //

always @ (posedge f_com)
begin
	d_com = 0;
	valA=0;
	valB=0;
	if(icode == 2 || icode ==4 || icode == 6 || icode == 10)
	begin
		valA = reg_file[rA];
	end
	if( icode == 6 )
	begin
		valB = reg_file[rB];
	end
	if( icode == 4 || icode == 5)
	begin
		valB = reg_file[rB];
	end

	// stack pointer 
	if(icode == 10 || icode == 8)
	begin
		valB = reg_file[4];
	end
	if(icode == 11 || icode==9)
	begin
		valA = reg_file[4];
	end
	d_com = 1;
	$display("Decode -- icode - %h, valA - %h, valB- %h",icode,valA,valB);
end

// ------- Write Back Stage -------- //
integer i=0;
always @(posedge clk)
begin
	if(icode == 5  || icode == 11)
	begin
		reg_file[rA] = valM;
		
	end
	if( (icode == 2 && cnd == 1) ||  icode == 3 || icode == 6)
	begin
		reg_file[rB] = valE;
	end
	if(icode == 8 || icode == 9 ||  icode== 11 || icode == 10)
	begin
		reg_file[4] = valE;
	end
	r1Val = reg_file[1];
	r2Val = reg_file[2];
	r0Val = reg_file[0];
	$display("write back -- Time -- %0t ps,icode - %h,cnd - %h, valE - %h, valM - %h",$time,icode,cnd, valE,valM);
	$display("REGISTER FILE");
	for(i=0;i<16;i = i+2)
	begin
		$display("R%0d - %d     ----     R%0d - %d",i,reg_file[i],i+1,reg_file[i+1]);
		
	end
	$display("\n\n");
end

endmodule

sequential/fetch/fetch.v
`timescale 1ns/1ps

module fetch(input [10:0] pc,output [3:0] icode,output [3:0] ifun,output [3:0] rA,output [3:0] rB,output [63:0] valC,output [10:0] valP,output instr_valid,output imem_error,output reg f_com);


reg [3:0] icode;
reg [3:0] ifun;
reg [3:0] rA;
reg [3:0] rB;
reg [63:0] valC;
reg [10:0] valP = 0;
reg instr_valid = 1;
reg imem_error =0;
reg [7:0] temp;
reg [10:0] pc_inc = 0;


// defining the instruction memory here.
reg [7:0] i_mem [0:1000];
initial begin
	$readmemh("instr_mem.txt",i_mem);
end
// End of instruction memory defining 



always @(pc)
begin
	f_com = 0;
	rA = 15;
	rB = 15;
	valP = pc;
	if (pc>1000) // This condition changes according to the size of the instruction memory.
		imem_error = 1;
	else 
	begin
		if(i_mem[pc][7:4]>11)
			instr_valid = 0;
		else
		begin
			icode = i_mem[pc][7:4];
			ifun = i_mem[pc][3:0];
			valP = valP+1;
			if(i_mem[pc][7:4] == 2 || i_mem[pc][7:4] == 3 ||i_mem[pc][7:4] == 4 || i_mem[pc][7:4] == 5 || i_mem[pc][7:4] == 6 || i_mem[pc][7:4] == 10 || i_mem[pc][7:4] == 11)
			begin
				
			       	valP = valP+1;
				if(i_mem[pc][7:4] == 3)
				begin
				       rA = 15;
			        	rB = i_mem[pc+1][3:0];
			       	end
				else if(i_mem[pc][7:4] == 10 || i_mem[pc][7:4] == 11)
				begin
					rB = 15;
					rA = i_mem[pc+1][7:4];
				end	
				else
				begin
					rA = i_mem[pc+1][7:4];
					rB = i_mem[pc+1][3:0];
				end
			end
			if(i_mem[pc][7:4] == 3 || i_mem[pc][7:4] == 4 ||i_mem[pc][7:4] == 5 || i_mem[pc][7:4] == 7 || i_mem[pc][7:4] == 8)
			begin
				if (i_mem[pc][7:4]==8 || i_mem[pc][7:4]==7)
				begin
				valC[7:0] = i_mem[pc+1];
				valC[15:8] = i_mem[pc+2];
				valC[23:16] = i_mem[pc+3];
				valC[31:24] = i_mem[pc+4];
				valC[39:32] = i_mem[pc+5];
				valC[47:40] = i_mem[pc+6];
				valC[55:48] = i_mem[pc+7];
				valC[63:56] = i_mem[pc+8];
				valP = valP+8;
				end
				else
				begin
				valC[7:0] = i_mem[pc+2];
				valC[15:8] = i_mem[pc+3];
				valC[23:16] = i_mem[pc+4];
				valC[31:24] = i_mem[pc+5];
				valC[39:32] = i_mem[pc+6];
				valC[47:40] = i_mem[pc+7];
				valC[55:48] = i_mem[pc+8];
				valC[63:56] = i_mem[pc+9];
				valP = valP+8;
				end
			end
			
		end
	end	
	
	if(icode == 0)
	begin
		$display("Stat -SHLT");
		$display("halt encounterd");
		#1;
		$finish;
	end
	$display("\n\n\n Fetch -- icode - %h, ifun -  %h, rA -%h, rB - %h, valc - %h, valP - %h, pc - %h", icode, ifun, rA, rB, valC, valP, pc);	
	f_com = 1;
end
endmodule

sequential/seq_processor.v
`timescale 1ns/1ps
`include "alu/alu.v"
`include "fetch/fetch.v"
`include "decode_writeback/decode.v"
`include "memory/memory.v"
`include "pcupdate/pcupdate.v"

module seq_processor;
wire [10:0] pc ;
wire [3:0] icode;
wire [3:0] ifun;
wire [3:0] rA;
wire [3:0] rB;
wire [63:0] valC;
wire [10:0] valP;
wire f_com;
wire d_com;
wire e_com;
// control condtions
wire instr_valid;
wire imem_error;
wire cnd;
wire dmem_error;

wire [63:0] valA;
wire [63:0] valB;
wire [63:0] valE;
wire [63:0] valM;
reg clk ;
wire [1:0] stat;
fetch call1(pc,icode,ifun,rA,rB,valC,valP,instr_valid,imem_error,f_com);
decode call2(clk,icode,rA,rB,valA,valB,valE,valM,cnd,d_com,f_com);
alu call3(icode,ifun,valA,valB,valC,valE,cnd,d_com,e_com);
memory call4(icode,valA,valE,valP,valM,imem_error,instr_valid,dmem_error,stat,e_com); // i took valB instead valA for stack pointer case
pcupdate call5(clk,icode,cnd,valC,valM,valP,pc);

parameter stop_time = 2000000000;
initial #stop_time $finish;


initial begin
	//$monitor("main  %d ",pc);
	$dumpfile("seq.vcd");
	$dumpvars(0,seq_processor);
	clk = 0;
end
always begin
//		if(icode==0)
//		begin
		//	$display("icode %d",icode);
//			#1;
//		clk=~clk;
	//		#5;
//			$finish;
//		end
//		else
		#1 clk = ~clk;
	end
endmodule

sequential/seq.vcd
$date
	Wed Mar 10 23:08:24 2021
$end
$version
	Icarus Verilog
$end
$timescale
	1ps
$end
$scope module seq_processor $end
$var wire 11 ! valP [10:0] $end
$var wire 64 " valM [63:0] $end
$var wire 64 # valE [63:0] $end
$var wire 64 $ valC [63:0] $end
$var wire 64 % valB [63:0] $end
$var wire 64 & valA [63:0] $end
$var wire 2 ' stat [1:0] $end
$var wire 4 ( rB [3:0] $end
$var wire 4 ) rA [3:0] $end
$var wire 11 * pc [10:0] $end
$var wire 1 + instr_valid $end
$var wire 1 , imem_error $end
$var wire 4 - ifun [3:0] $end
$var wire 4 . icode [3:0] $end
$var wire 1 / f_com $end
$var wire 1 0 e_com $end
$var wire 1 1 dmem_error $end
$var wire 1 2 d_com $end
$var wire 1 3 cnd $end
$var reg 1 4 clk $end
$scope module call1 $end
$var wire 11 5 pc [10:0] $end
$var reg 1 / f_com $end
$var reg 4 6 icode [3:0] $end
$var reg 4 7 ifun [3:0] $end
$var reg 1 , imem_error $end
$var reg 1 + instr_valid $end
$var reg 11 8 pc_inc [10:0] $end
$var reg 4 9 rA [3:0] $end
$var reg 4 : rB [3:0] $end
$var reg 64 ; valC [63:0] $end
$var reg 11 < valP [10:0] $end
$upscope $end
$scope module call2 $end
$var wire 1 4 clk $end
$var wire 1 / f_com $end
$var wire 4 = icode [3:0] $end
$var wire 4 > rA [3:0] $end
$var wire 4 ? rB [3:0] $end
$var wire 64 @ valM [63:0] $end
$var wire 64 A valE [63:0] $end
$var wire 1 3 cnd $end
$var reg 1 B complete $end
$var reg 1 2 d_com $end
$var reg 64 C r0Val [63:0] $end
$var reg 64 D r1Val [63:0] $end
$var reg 64 E r2Val [63:0] $end
$var reg 64 F valA [63:0] $end
$var reg 64 G valB [63:0] $end
$var integer 32 H i [31:0] $end
$upscope $end
$scope module call3 $end
$var wire 1 2 d_com $end
$var wire 4 I icode [3:0] $end
$var wire 4 J ifun [3:0] $end
$var wire 64 K valA [63:0] $end
$var wire 64 L valB [63:0] $end
$var wire 64 M valC [63:0] $end
$var reg 64 N a [63:0] $end
$var reg 64 O b [63:0] $end
$var reg 3 P cc [2:0] $end
$var reg 1 3 cnd $end
$var reg 1 0 e_com $end
$var reg 3 Q fun [2:0] $end
$var reg 64 R valE [63:0] $end
$upscope $end
$scope module call4 $end
$var wire 1 0 e_com $end
$var wire 4 S icode [3:0] $end
$var wire 1 , imem_error $end
$var wire 1 + instr_valid $end
$var wire 64 T valA [63:0] $end
$var wire 64 U valE [63:0] $end
$var wire 11 V valP [10:0] $end
$var reg 64 W address [63:0] $end
$var reg 64 X data [63:0] $end
$var reg 1 1 dmem_error $end
$var reg 1 Y read $end
$var reg 2 Z stat [1:0] $end
$var reg 64 [ valM [63:0] $end
$var reg 1 \ write $end
$upscope $end
$scope module call5 $end
$var wire 1 4 clk $end
$var wire 1 3 cnd $end
$var wire 4 ] icode [3:0] $end
$var wire 64 ^ valC [63:0] $end
$var wire 64 _ valM [63:0] $end
$var wire 11 ` valP [10:0] $end
$var reg 11 a pc [10:0] $end
$upscope $end
$upscope $end
$enddefinitions $end
#0
$dumpvars
b0 a
b1010 `
bx _
b100 ^
b11 ]
0\
bx [
b0 Z
0Y
b0 X
b0 W
b1010 V
b100 U
b0 T
b11 S
b100 R
b0 Q
b0 P
b0 O
b100 N
b100 M
b0 L
b0 K
b0 J
b11 I
b0 H
b0 G
b0 F
bx E
bx D
bx C
xB
b100 A
bx @
b1010 ?
b1111 >
b11 =
b1010 <
b100 ;
b1010 :
b1111 9
b0 8
b0 7
b11 6
b0 5
04
x3
12
01
10
1/
b11 .
b0 -
0,
1+
b0 *
b1111 )
b1010 (
b0 '
b0 &
b0 %
b100 $
b100 #
bx "
b1010 !
$end
#1000
b110 #
b110 A
b110 R
b110 U
b110 N
10
12
b110 $
b110 ;
b110 M
b110 ^
b10100 !
b10100 <
b10100 V
b10100 `
b1011 (
b1011 :
b1011 ?
1/
b10000 H
b0 C
b0 E
b0 D
b1010 *
b1010 5
b1010 a
14
#2000
04
#3000
13
b100 #
b100 A
b100 R
b100 U
b100 N
10
b100 &
b100 F
b100 K
b100 T
12
b1010 )
b1010 9
b1010 >
b10110 !
b10110 <
b10110 V
b10110 `
b10 .
b10 6
b10 =
b10 I
b10 S
b10 ]
b1 (
b1 :
b1 ?
1/
b10100 *
b10100 5
b10100 a
b10000 H
14
#4000
04
#5000
13
b110 #
b110 A
b110 R
b110 U
b110 N
10
b110 &
b110 F
b110 K
b110 T
12
b11000 !
b11000 <
b11000 V
b11000 `
b10 (
b10 :
b10 ?
b1011 )
b1011 9
b1011 >
1/
b10000 H
b100 D
b10110 *
b10110 5
b10110 a
14
#6000
04
#7000
13
10
b110 &
b110 F
b110 K
b110 T
12
b11010 !
b11010 <
b11010 V
b11010 `
b0 (
b0 :
b0 ?
b10 )
b10 9
b10 >
1/
b11000 *
b11000 5
b11000 a
b10000 H
b110 E
14
#8000
04
#9000
b10 #
b10 A
b10 R
b10 U
b1 Q
b110 O
b100 N
10
b110 %
b110 G
b110 L
b100 &
b100 F
b100 K
b100 T
12
b11100 !
b11100 <
b11100 V
b11100 `
b1 -
b1 7
b1 J
b110 .
b110 6
b110 =
b110 I
b110 S
b110 ]
b0 (
b0 :
b0 ?
b1 )
b1 9
b1 >
1/
b10000 H
b110 C
b11010 *
b11010 5
b11010 a
14
#10000
04
#11000
03
10
b0 %
b0 G
b0 L
b0 &
b0 F
b0 K
b0 T
12
b1010011 $
b1010011 ;
b1010011 M
b1010011 ^
b100101 !
b100101 <
b100101 V
b100101 `
b11 -
b11 7
b11 J
b111 .
b111 6
b111 =
b111 I
b111 S
b111 ]
b1111 (
b1111 :
b1111 ?
b1111 )
b1111 9
b1111 >
1/
b11100 *
b11100 5
b11100 a
b10000 H
b10 C
14
#12000
04
#13000
13
10
12
b1000100 $
b1000100 ;
b1000100 M
b1000100 ^
b101110 !
b101110 <
b101110 V
b101110 `
b110 -
b110 7
b110 J
1/
b10000 H
b100101 *
b100101 5
b100101 a
14
#14000
04
#15000
13
b110 #
b110 A
b110 R
b110 U
b0 Q
b0 O
b110 N
10
b110 &
b110 F
b110 K
b110 T
12
b0 (
b0 :
b0 ?
b10 )
b10 9
b10 >
b0 -
b0 7
b0 J
b10 .
b10 6
b10 =
b10 I
b10 S
b10 ]
b1000110 !
b1000110 <
b1000110 V
b1000110 `
1/
b1000100 *
b1000100 5
b1000100 a
b10000 H
14
#16000
04
#17000
13
b100 #
b100 A
b100 R
b100 U
b100 N
10
b100 &
b100 F
b100 K
b100 T
12
b1001000 !
b1001000 <
b1001000 V
b1001000 `
b10 (
b10 :
b10 ?
b1 )
b1 9
b1 >
1/
b10000 H
b110 C
b1000110 *
b1000110 5
b1000110 a
14
#18000
04
#19000
13
b110 #
b110 A
b110 R
b110 U
b110 N
10
b110 &
b110 F
b110 K
b110 T
12
b1001010 !
b1001010 <
b1001010 V
b1001010 `
b1 (
b1 :
b1 ?
b0 )
b0 9
b0 >
1/
b1001000 *
b1001000 5
b1001000 a
b10000 H
b100 E
14
#20000
04
#21000
13
10
b0 &
b0 F
b0 K
b0 T
12
b101110 $
b101110 ;
b101110 M
b101110 ^
b1010011 !
b1010011 <
b1010011 V
b1010011 `
b111 .
b111 6
b111 =
b111 I
b111 S
b111 ]
b1111 (
b1111 :
b1111 ?
b1111 )
b1111 9
b1111 >
1/
b10000 H
b110 D
b1001010 *
b1001010 5
b1001010 a
14
#22000
04
#23000
b10 #
b10 A
b10 R
b10 U
b1 Q
b110 O
b100 N
10
b110 %
b110 G
b110 L
b100 &
b100 F
b100 K
b100 T
12
b1 (
b1 :
b1 ?
b10 )
b10 9
b10 >
b1 -
b1 7
b1 J
b110 .
b110 6
b110 =
b110 I
b110 S
b110 ]
b110000 !
b110000 <
b110000 V
b110000 `
1/
b101110 *
b101110 5
b101110 a
b10000 H
14
#24000
04
#25000
03
10
b0 %
b0 G
b0 L
b0 &
b0 F
b0 K
b0 T
12
b1010011 $
b1010011 ;
b1010011 M
b1010011 ^
b111001 !
b111001 <
b111001 V
b111001 `
b11 -
b11 7
b11 J
b111 .
b111 6
b111 =
b111 I
b111 S
b111 ]
b1111 (
b1111 :
b1111 ?
b1111 )
b1111 9
b1111 >
1/
b10000 H
b10 D
b110000 *
b110000 5
b110000 a
14
#26000
04
#27000
13
10
12
b101110 $
b101110 ;
b101110 M
b101110 ^
b1000010 !
b1000010 <
b1000010 V
b1000010 `
b110 -
b110 7
b110 J
1/
b111001 *
b111001 5
b111001 a
b10000 H
14
#28000
04
#29000
b10 P
b1111111111111111111111111111111111111111111111111111111111111110 #
b1111111111111111111111111111111111111111111111111111111111111110 A
b1111111111111111111111111111111111111111111111111111111111111110 R
b1111111111111111111111111111111111111111111111111111111111111110 U
b10 O
10
b10 %
b10 G
b10 L
b100 &
b100 F
b100 K
b100 T
12
b1 (
b1 :
b1 ?
b10 )
b10 9
b10 >
b1 -
b1 7
b1 J
b110 .
b110 6
b110 =
b110 I
b110 S
b110 ]
b110000 !
b110000 <
b110000 V
b110000 `
1/
b10000 H
b101110 *
b101110 5
b101110 a
14
#30000
04
#31000
03
10
b0 %
b0 G
b0 L
b0 &
b0 F
b0 K
b0 T
12
b1010011 $
b1010011 ;
b1010011 M
b1010011 ^
b111001 !
b111001 <
b111001 V
b111001 `
b11 -
b11 7
b11 J
b111 .
b111 6
b111 =
b111 I
b111 S
b111 ]
b1111 (
b1111 :
b1111 ?
b1111 )
b1111 9
b1111 >
1/
b110000 *
b110000 5
b110000 a
b10000 H
b1111111111111111111111111111111111111111111111111111111111111110 D
14
#32000
04
#33000
10
12
b101110 $
b101110 ;
b101110 M
b101110 ^
b1000010 !
b1000010 <
b1000010 V
b1000010 `
b110 -
b110 7
b110 J
1/
b10000 H
b111001 *
b111001 5
b111001 a
14
#34000
04
#35000
b10 #
b10 A
b10 R
b10 U
b0 P
b0 Q
b1111111111111111111111111111111111111111111111111111111111111110 O
10
b1111111111111111111111111111111111111111111111111111111111111110 %
b1111111111111111111111111111111111111111111111111111111111111110 G
b1111111111111111111111111111111111111111111111111111111111111110 L
b100 &
b100 F
b100 K
b100 T
12
b1 (
b1 :
b1 ?
b10 )
b10 9
b10 >
b1000100 !
b1000100 <
b1000100 V
b1000100 `
b0 -
b0 7
b0 J
b110 .
b110 6
b110 =
b110 I
b110 S
b110 ]
1/
b1000010 *
b1000010 5
b1000010 a
b10000 H
14
#36000
04
#37000
13
b100 #
b100 A
b100 R
b100 U
b0 O
10
b0 %
b0 G
b0 L
b100 &
b100 F
b100 K
b100 T
12
b1000110 !
b1000110 <
b1000110 V
b1000110 `
b10 .
b10 6
b10 =
b10 I
b10 S
b10 ]
b0 (
b0 :
b0 ?
b10 )
b10 9
b10 >
1/
b10000 H
b10 D
b1000100 *
b1000100 5
b1000100 a
14
#38000
04
#39000
13
b10 #
b10 A
b10 R
b10 U
b10 N
10
b10 &
b10 F
b10 K
b10 T
12
b1001000 !
b1001000 <
b1001000 V
b1001000 `
b10 (
b10 :
b10 ?
b1 )
b1 9
b1 >
1/
b1000110 *
b1000110 5
b1000110 a
b10000 H
b100 C
14
#40000
04
#41000
13
b100 #
b100 A
b100 R
b100 U
b100 N
10
b100 &
b100 F
b100 K
b100 T
12
b1001010 !
b1001010 <
b1001010 V
b1001010 `
b1 (
b1 :
b1 ?
b0 )
b0 9
b0 >
1/
b10000 H
b10 E
b1001000 *
b1001000 5
b1001000 a
14
#42000
04
#43000
13
10
b0 &
b0 F
b0 K
b0 T
12
b1010011 !
b1010011 <
b1010011 V
b1010011 `
b111 .
b111 6
b111 =
b111 I
b111 S
b111 ]
b1111 (
b1111 :
b1111 ?
b1111 )
b1111 9
b1111 >
1/
b1001010 *
b1001010 5
b1001010 a
b10000 H
b100 D
14
#44000
04
#45000
b10 #
b10 A
b10 R
b10 U
b1 Q
b100 O
b10 N
10
b100 %
b100 G
b100 L
b10 &
b10 F
b10 K
b10 T
12
b1 (
b1 :
b1 ?
b10 )
b10 9
b10 >
b1 -
b1 7
b1 J
b110 .
b110 6
b110 =
b110 I
b110 S
b110 ]
b110000 !
b110000 <
b110000 V
b110000 `
1/
b10000 H
b101110 *
b101110 5
b101110 a
14
#46000
04
#47000
03
10
b0 %
b0 G
b0 L
b0 &
b0 F
b0 K
b0 T
12
b1010011 $
b1010011 ;
b1010011 M
b1010011 ^
b111001 !
b111001 <
b111001 V
b111001 `
b11 -
b11 7
b11 J
b111 .
b111 6
b111 =
b111 I
b111 S
b111 ]
b1111 (
b1111 :
b1111 ?
b1111 )
b1111 9
b1111 >
1/
b110000 *
b110000 5
b110000 a
b10000 H
b10 D
14
#48000
04
#49000
13
10
12
b101110 $
b101110 ;
b101110 M
b101110 ^
b1000010 !
b1000010 <
b1000010 V
b1000010 `
b110 -
b110 7
b110 J
1/
b10000 H
b111001 *
b111001 5
b111001 a
14
#50000
04
#51000
b1 P
b0 #
b0 A
b0 R
b0 U
b10 O
10
b10 %
b10 G
b10 L
b10 &
b10 F
b10 K
b10 T
12
b1 (
b1 :
b1 ?
b10 )
b10 9
b10 >
b1 -
b1 7
b1 J
b110 .
b110 6
b110 =
b110 I
b110 S
b110 ]
b110000 !
b110000 <
b110000 V
b110000 `
1/
b101110 *
b101110 5
b101110 a
b10000 H
14
#52000
04
#53000
13
10
b0 %
b0 G
b0 L
b0 &
b0 F
b0 K
b0 T
12
b1010011 $
b1010011 ;
b1010011 M
b1010011 ^
b111001 !
b111001 <
b111001 V
b111001 `
b11 -
b11 7
b11 J
b111 .
b111 6
b111 =
b111 I
b111 S
b111 ]
b1111 (
b1111 :
b1111 ?
b1111 )
b1111 9
b1111 >
1/
b10000 H
b0 D
b110000 *
b110000 5
b110000 a
14
#54000
04
#55000
13
b10 #
b10 A
b10 R
b10 U
b0 Q
b0 O
10
b10 &
b10 F
b10 K
b10 T
12
b0 (
b0 :
b0 ?
b10 )
b10 9
b10 >
b0 -
b0 7
b0 J
b10 .
b10 6
b10 =
b10 I
b10 S
b10 ]
b1010101 !
b1010101 <
b1010101 V
b1010101 `
1/
b1010011 *
b1010011 5
b1010011 a
b10000 H
14
#56000
04
